{"title":"위메프 공연티켓 ─ 티켓오픈공지","url":"https://ticket.wemakeprice.com/opennotice","favicon":"https://ticket.wemakeprice.com/favicon.ico","elements":[{"title":"HAUS OF WONDER(하우스 오브 원더) 티켓오픈 안내 N","contents":"2022.06.03(금) 14:00","link":"https://ticket.wemakeprice.com/opennotice/870","retrieved":1653891724717,"image":"https://t-img1.wemep.co.kr/wmp-topen/02/202205/30/ayaryeqjaogm.jpg"},{"title":"세종 어린이 시리즈 Ⅱ 가족음악극 〈백조마을의 차이콥스키〉 티켓오픈 안내 N","contents":"2022.06.03(금) 16:00","link":"https://ticket.wemakeprice.com/opennotice/869","retrieved":1653873142903,"image":"https://t-img1.wemep.co.kr/wmp-topen/55/202205/30/xs0debeblvwk.jpg"},{"title":"타루 콘서트 새로운 길 오늘도 내일도 티켓오픈 안내","contents":"2022.05.30(월) 16:00","link":"https://ticket.wemakeprice.com/opennotice/868","retrieved":1653556507856,"image":"https://t-img1.wemep.co.kr/wmp-topen/44/202205/26/ntbyt6epszfs.jpg"},{"title":"W필하모닉오케스트라 〈말러 교향곡 1번: 거인〉 티켓오픈 안내","contents":"2022.05.27(금) 10:00","link":"https://ticket.wemakeprice.com/opennotice/867","retrieved":1653376440630,"image":"https://t-img1.wemep.co.kr/wmp-topen/05/202205/24/4nmqv1tj3tbo.jpg"},{"title":"원더러스트 코리아 2022 티켓오픈 안내","contents":"2022.05.23(월) 14:00","link":"https://ticket.wemakeprice.com/opennotice/866","retrieved":1653187579481,"image":"https://t-img1.wemep.co.kr/wmp-topen/14/202205/23/i6biwidac3zi.png"},{"title":"[공지] 2022년도 티켓 배송료 인상 안내","contents":"추후공지예정","link":"https://ticket.wemakeprice.com/opennotice/865","retrieved":1653187579489,"image":"https://t-img1.wemep.co.kr/wmp-topen/33/202205/18/ejhlvgebrnu8.jpg"},{"title":"디뮤지엄 〈어쨌든, 사랑: Romantic Days〉 티켓오픈 안내","contents":"2022.05.24(화) 00:00","link":"https://ticket.wemakeprice.com/opennotice/864","retrieved":1653187579491,"image":"https://t-img1.wemep.co.kr/wmp-topen/27/202205/18/mhrgqcdzy6sv.jpg"},{"title":"청춘페스티벌 2022 : 오히려 좋아 티켓오픈 안내","contents":"2022.05.18(수) 14:00","link":"https://ticket.wemakeprice.com/opennotice/863","retrieved":1653187579494,"image":"https://t-img1.wemep.co.kr/wmp-topen/41/202205/18/6vjghj3dxch0.jpg"},{"title":"레인보우 페스티벌 2022 - 얼리버드 티켓오픈 안내","contents":"2022.05.19(목) 14:00","link":"https://ticket.wemakeprice.com/opennotice/862","retrieved":1653187579496,"image":"https://t-img1.wemep.co.kr/wmp-topen/48/202205/16/m2jrltm5ue8r.jpg"},{"title":"가족뮤지컬 〈모여라 트니프렌즈! : 트니트니 탐험대〉 티켓오픈 안내","contents":"2022.05.18(수) 11:00","link":"https://ticket.wemakeprice.com/opennotice/861","retrieved":1653187579512,"image":"https://t-img1.wemep.co.kr/wmp-topen/21/202205/16/gjhpsrlkojx1.jpg"}]}